[
  {
    "frame": 0,
    "face": {
      "leye": 110,
      "reye": 210,
      "mouth": 311,
      "cheek": 402
    }
  },
  {
    "frame": 3,
    "face": {
      "leye": 110,
      "reye": 210,
      "mouth": 302,
      "cheek": 402
    }
  },
  {
    "frame": 8,
    "face": {
      "leye": 110,
      "reye": 210,
      "mouth": 311,
      "cheek": 402
    }
  },
  {
    "frame": 13,
    "face": {
      "leye": 110,
      "reye": 210,
      "mouth": 302,
      "cheek": 402
    }
  },
  {
    "frame": 19,
    "face": {
      "leye": 119,
      "reye": 220,
      "mouth": 322,
      "cheek": 400
    }
  }
]